{
    "dc31919": {
        "type": "destinationcharger",
        "statId": "dc31919",
        "statNm": "간절곶 까르마레 펜션",
        "bnm": "데스티네이션차저",
        "lat": 35.359468,
        "lng": 129.333839,
        "addr": "울산 울주군 서생면 불안길 30-19",
        "phone": "052-242-5600",
        "webSite": "http://www.calmare.co.kr/",
        "accessHours": "고객과 게스트가 연중무휴 24시간 이용 가능",
        "stallCount": 1,
        "powerKilowattL": 7
    },
    "dc80940": {
        "type": "destinationcharger",
        "statId": "dc80940",
        "statNm": "강남N타워",
        "bnm": "데스티네이션차저",
        "lat": 37.499893,
        "lng": 127.032379,
        "addr": "서울 강남구 테헤란로 129",
        "phone": "262505150",
        "webSite": null,
        "accessHours": "연중무휴 24시간 이용 가능 주차비가 부과됩니다. 직접 주차",
        "stallCount": 6,
        "powerKilowattL": 7
    },
    "GeonmokPlaza": {
        "type": "destinationcharger",
        "statId": "GeonmokPlaza",
        "statNm": "건목프라자",
        "bnm": "데스티네이션차저",
        "lat": 37.4412,
        "lng": 126.9022,
        "addr": "서울 금천구 시흥대로27길 22",
        "phone": null,
        "webSite": null,
        "accessHours": "일반인이 연중무휴 24시간 이용 가능. 직접 주차",
        "stallCount": 20,
        "powerKilowattL": 7
    },
    "gwanggyosupercharger": {
        "type": "destinationcharger",
        "statId": "gwanggyosupercharger",
        "statNm": "수원 광교 - 법조타운",
        "bnm": "데스티네이션차저",
        "lat": 37.293412,
        "lng": 127.0701665,
        "addr": "경기 수원시 영통구 법조로149번길 269, 광교 법원 주차장 3F",
        "phone": null,
        "webSite": null,
        "accessHours": "일반인이 연중무휴 24시간 이용 가능. 직접 주차",
        "stallCount": 1,
        "powerKilowattL": 10
    },
    "gwanggyolakesupercharger": {
        "type": "destinationcharger",
        "statId": "gwanggyolakesupercharger",
        "statNm": "수원 광교 - 롯데아울렛",
        "bnm": "데스티네이션차저",
        "lat": 37.28656,
        "lng": 127.05594,
        "addr": "경기 수원시 영통구 도청로 10 롯데아울렛 광교점 지하4층 A3 기둥 인근",
        "phone": null,
        "webSite": null,
        "accessHours": "일반인이 연중무휴 24시간 이용 가능. 직접 주차",
        "stallCount": 3,
        "powerKilowattL": 7
    },
    "gwangmyeongsupercharger": {
        "type": "destinationcharger",
        "statId": "gwangmyeongsupercharger",
        "statNm": "광명 - AK플라자",
        "bnm": "데스티네이션차저",
        "lat": 37.41866,
        "lng": 126.88073,
        "addr": "경기 광명시 양지로 17, 광명 유플래닛 B5F",
        "phone": null,
        "webSite": null,
        "accessHours": "일반인이 연중무휴 24시간 이용 가능. 직접 주차",
        "stallCount": 6,
        "powerKilowattL": 7
    },
    "gunpogeumjeongakplaza": {
        "type": "destinationcharger",
        "statId": "gunpogeumjeongakplaza",
        "statNm": "군포 - AK플라자",
        "bnm": "데스티네이션차저",
        "lat": 37.3715,
        "lng": 126.9454,
        "addr": "경기 군포시 엘에스로 143, AK PLAZA 금정점 B2 4구역",
        "phone": null,
        "webSite": null,
        "accessHours": "일반인이 연중무휴 24시간 이용 가능. 직접 주차",
        "stallCount": 3,
        "powerKilowattL": 7
    },
    "dc27187": {
        "type": "destinationcharger",
        "statId": "dc27187",
        "statNm": "그랜드 워커힐 서울",
        "bnm": "데스티네이션차저",
        "lat": 37.555093,
        "lng": 127.110951,
        "addr": "서울 광진구 워커힐로 177",
        "phone": "02-455-5000",
        "webSite": "https://www.walkerhill.com/grandwalkerhillseoul/en/",
        "accessHours": "고객과 게스트가 연중무휴 24시간 이용 가능.",
        "stallCount": 3,
        "powerKilowattL": 16
    },
    "dc28243": {
        "type": "destinationcharger",
        "statId": "dc28243",
        "statNm": "그랜드 하얏트 인천 웨스트타워",
        "bnm": "데스티네이션차저",
        "lat": 37.439949,
        "lng": 126.456126,
        "addr": "인천 중구 영종해안남로321번길 190",
        "phone": "032-745-1234",
        "webSite": "https://incheon.grand.hyatt.com/ko/hotel/home.html/",
        "accessHours": "고객과 게스트가 연중무휴 24시간 이용 가능.",
        "stallCount": 2,
        "powerKilowattL": 16
    },
    "dc27312": {
        "type": "destinationcharger",
        "statId": "dc27312",
        "statNm": "그랜드 하얏트 인천 이스트타워",
        "bnm": "데스티네이션차저",
        "lat": 37.440432,
        "lng": 126.457467,
        "addr": "인천 중구 영종해안남로321번길 208",
        "phone": "032-745-1234",
        "webSite": "https://incheon.grand.hyatt.com/ko/hotel/home.html/",
        "accessHours": "고객과 게스트가 연중무휴 24시간 이용 가능.",
        "stallCount": 2,
        "powerKilowattL": 16
    },
    "55540": {
        "type": "destinationcharger",
        "statId": "55540",
        "statNm": "그리드위즈 연구동",
        "bnm": "데스티네이션차저",
        "lat": 37.391081,
        "lng": 127.0564519,
        "addr": "경기 성남시 분당구 하오개로344번길 2",
        "phone": "031-698-3387",
        "webSite": "http://gridwiz.com",
        "accessHours": "고객과 게스트가 연중무휴 24시간 이용 가능.",
        "stallCount": 1,
        "powerKilowattL": 11
    },
    "dc71701": {
        "type": "destinationcharger",
        "statId": "dc71701",
        "statNm": "그린 빌딩",
        "bnm": "데스티네이션차저",
        "lat": 35.7295755,
        "lng": 128.268047,
        "addr": "경북 고령군 대가야읍 왕릉로 114",
        "phone": "054-956-7007",
        "webSite": null,
        "accessHours": "일반인이 연중무휴 24시간 이용 가능. 직접 주차",
        "stallCount": 2,
        "powerKilowattL": 6
    },
    "gimposupercharger": {
        "type": "destinationcharger",
        "statId": "gimposupercharger",
        "statNm": "김포 구래",
        "bnm": "데스티네이션차저",
        "lat": 37.6463583,
        "lng": 126.6303188,
        "addr": "경기 김포시 김포한강4로 487, 카림애비뉴 김포 B1F",
        "phone": null,
        "webSite": null,
        "accessHours": "일반인이 연중무휴 24시간 이용 가능. 직접 주차",
        "stallCount": 3,
        "powerKilowattL": 7
    },
    "dc28128": {
        "type": "destinationcharger",
        "statId": "dc28128",
        "statNm": "대구백화점 프라자점",
        "bnm": "데스티네이션차저",
        "lat": 128.606333,
        "lng": 128.606333,
        "addr": "대구 중구 명덕로 333",
        "phone": "053-426-1234",
        "webSite": "http://www.debec.co.kr/",
        "accessHours": "고객과 게스트가 연중무휴 24시간 이용 가능.",
        "stallCount": 3,
        "powerKilowattL": 7
    },
    "Daejeon": {
        "type": "destinationcharger",
        "statId": "Daejeon",
        "statNm": "대전 서구 - 롯데백화점",
        "bnm": "데스티네이션차저",
        "lat": 36.34076,
        "lng": 127.38949,
        "addr": "대전 서구 계룡로 598, 롯데백화점 대전 B4F",
        "phone": null,
        "webSite": null,
        "accessHours": "일반인이 연중무휴 24시간 이용 가능. 직접 주차",
        "stallCount": 4,
        "powerKilowattL": 7
    },
    "dc27298": {
        "type": "destinationcharger",
        "statId": "dc27298",
        "statNm": "더 클라우드 호텔",
        "bnm": "데스티네이션차저",
        "lat": 33.468968,
        "lng": 126.935391,
        "addr": "제주특별자치도 서귀포시 성산읍 한도로 269-37",
        "phone": "064-783-8366",
        "webSite": "http://www.cloudhotel.co.kr/",
        "accessHours": "고객과 게스트가 연중무휴 24시간 이용 가능.",
        "stallCount": 2,
        "powerKilowattL": 16
    },
    "dc27197": {
        "type": "destinationcharger",
        "statId": "dc27197",
        "statNm": "더 플라자 호텔",
        "bnm": "데스티네이션차저",
        "lat": 37.564637,
        "lng": 126.97811,
        "addr": "서울 중구 소공로 119",
        "phone": "02-771-2200",
        "webSite": "http://www.hoteltheplaza.com",
        "accessHours": "고객과 게스트가 연중무휴 24시간 이용 가능.",
        "stallCount": 3,
        "powerKilowattL": 16
    },
    "dongtansupercharger": {
        "type": "destinationcharger",
        "statId": "dongtansupercharger",
        "statNm": "화성 동탄 - 롯데백화점",
        "bnm": "데스티네이션차저",
        "lat": 37.2008314,
        "lng": 127.0974318,
        "addr": "경기 화성시 동탄구 동탄역로 160, 롯데백화점 동탄 B4F",
        "phone": "1577-0001",
        "webSite": "https://www.lottedongtan.com/",
        "accessHours": "일반인이 연중무휴 24시간 이용 가능. 직접 주차",
        "stallCount": 3,
        "powerKilowattL": 7
    },
    "55551": {
        "type": "destinationcharger",
        "statId": "55551",
        "statNm": "디테라스",
        "bnm": "데스티네이션차저",
        "lat": 37.403642,
        "lng": 127.109051,
        "addr": "경기 성남시 분당구 판교로319번길 13",
        "phone": "031-609-7999",
        "webSite": "http://deterrace.com/",
        "accessHours": "고객과 게스트가 연중무휴 24시간 이용 가능.",
        "stallCount": 1,
        "powerKilowattL": 16
    },
    "dc41686": {
        "type": "destinationcharger",
        "statId": "dc41686",
        "statNm": "라이즈 오토그래프콜렉션 호텔",
        "bnm": "데스티네이션차저",
        "lat": 37.5544325,
        "lng": 126.9211742,
        "addr": "서울 마포구 양화로 130",
        "phone": "02-330-7700",
        "webSite": "https://www.rysehotel.com/",
        "accessHours": "고객과 게스트가 연중무휴 24시간 이용 가능.",
        "stallCount": 2,
        "powerKilowattL": 6
    },
    "dc57041": {
        "type": "destinationcharger",
        "statId": "dc57041",
        "statNm": "라임 비치 펜션",
        "bnm": "데스티네이션차저",
        "lat": 37.813008,
        "lng": 128.895208,
        "addr": "강원특별자치도 강릉시 해안로 651-17",
        "phone": "010-2603-5436",
        "webSite": "http://www.limebeach.co.kr",
        "accessHours": "고객과 게스트가 연중무휴 24시간 이용 가능. 직접 주차",
        "stallCount": 2,
        "powerKilowattL": 6
    },
    "dc27196": {
        "type": "destinationcharger",
        "statId": "dc27196",
        "statNm": "렉스필드 CC",
        "bnm": "데스티네이션차저",
        "lat": 37.401817,
        "lng": 127.422181,
        "addr": "경기 여주시 산북면 광여로 1115",
        "phone": "031-880-0300",
        "webSite": "https://www.rexfield.com/",
        "accessHours": "고객과 게스트가 연중무휴 24시간 이용 가능.",
        "stallCount": 2,
        "powerKilowattL": 16
    },
    "dc66000": {
        "type": "destinationcharger",
        "statId": "dc66000",
        "statNm": "마리오 아울렛",
        "bnm": "데스티네이션차저",
        "lat": 37.478524,
        "lng": 126.8847098,
        "addr": "서울 금천구 벚꽃로 266",
        "phone": "02-2109-7000",
        "webSite": "http://www.mariooutlet.co.kr/",
        "accessHours": "고객과 게스트가 연중무휴 24시간 이용 가능. 직접 주차",
        "stallCount": 2,
        "powerKilowattL": 6
    },
    "dc43100": {
        "type": "destinationcharger",
        "statId": "dc43100",
        "statNm": "모노리스제주파크",
        "bnm": "데스티네이션차저",
        "lat": 33.3907356,
        "lng": 126.3658468,
        "addr": "제주특별자치도 제주시 애월읍 천덕로 880-24",
        "phone": "070-4900-2230",
        "webSite": "http://monolith.co.kr/",
        "accessHours": "일반인이 연중무휴 24시간 이용 가능.",
        "stallCount": 7,
        "powerKilowattL": 6
    },
    "chungjumodaoutletsupercharger": {
        "type": "destinationcharger",
        "statId": "chungjumodaoutletsupercharger",
        "statNm": "충주 - 모다아울렛",
        "bnm": "데스티네이션차저",
        "lat": 36.961,
        "lng": 127.8998,
        "addr": "충북 충주시 중원대로 3683",
        "phone": null,
        "webSite": null,
        "accessHours": "일반인이 연중무휴 24시간 이용 가능. 직접 주차",
        "stallCount": 3,
        "powerKilowattL": 7
    },
    "incheonmichuholsupercharger": {
        "type": "destinationcharger",
        "statId": "incheonmichuholsupercharger",
        "statNm": "인천 미추홀 - 앨리웨이",
        "bnm": "데스티네이션차저",
        "lat": 37.470593,
        "lng": 126.664744,
        "addr": "인천 미추홀구 숙골로88번길 12, 앨리웨이 인천 B4F",
        "phone": null,
        "webSite": null,
        "accessHours": "일반인이 연중무휴 24시간 이용 가능. 직접 주차",
        "stallCount": 6,
        "powerKilowattL": 7
    },
    "dc636162": {
        "type": "destinationcharger",
        "statId": "dc636162",
        "statNm": "보키하우스",
        "bnm": "데스티네이션차저",
        "lat": 38.3079193,
        "lng": 128.5413247,
        "addr": "강원특별자치도 고성군 죽왕면 자작도선사길 110",
        "phone": "033-631-0303",
        "webSite": "www.bokeehouse.com",
        "accessHours": "연중무휴 24시간 이용 가능 직접 주차",
        "stallCount": 4,
        "powerKilowattL": 19
    },
    "busangijangsupercharger": {
        "type": "destinationcharger",
        "statId": "busangijangsupercharger",
        "statNm": "부산 기장 - 롯데프리미엄아울렛",
        "bnm": "데스티네이션차저",
        "lat": 35.1931,
        "lng": 129.2115,
        "addr": "부산 기장군 기장읍 기장해안로 147 롯데프리미엄아울렛 동부산점",
        "phone": null,
        "webSite": null,
        "accessHours": "일반인이 연중무휴 24시간 이용 가능. 직접 주차",
        "stallCount": 6,
        "powerKilowattL": 7
    },
    "buyeosupercharger": {
        "type": "destinationcharger",
        "statId": "buyeosupercharger",
        "statNm": "부여 - 롯데프리미엄아울렛",
        "bnm": "데스티네이션차저",
        "lat": 36.305926,
        "lng": 126.900338,
        "addr": "충남 부여군 규암면 백제문로 387, 롯데아울렛 부여",
        "phone": "041-435-2500",
        "webSite": null,
        "accessHours": "일반인이 연중무휴 24시간 이용 가능. 직접 주차",
        "stallCount": 5,
        "powerKilowattL": 7
    },
    "teslabucheonlottedepartmentsupercharger": {
        "type": "destinationcharger",
        "statId": "teslabucheonlottedepartmentsupercharger",
        "statNm": "부천 ",
        "bnm": "데스티네이션차저",
        "lat": 37.50255,
        "lng": 126.775018,
        "addr": "경기 부천시 원미구 길주로 300(지하4층 E3)",
        "phone": null,
        "webSite": null,
        "accessHours": "일반인이 연중무휴 24시간 이용 가능. 직접 주차",
        "stallCount": 7,
        "powerKilowattL": 7
    },
    "dc572132": {
        "type": "destinationcharger",
        "statId": "dc572132",
        "statNm": "사랑채 한방오리",
        "bnm": "데스티네이션차저",
        "lat": 35.234815,
        "lng": 128.879821,
        "addr": "경남 김해시 분성로307번길 16",
        "phone": "055-325-5292",
        "webSite": null,
        "accessHours": "일반인이 연중무휴 24시간 이용 가능. 직접 주차",
        "stallCount": 3,
        "powerKilowattL": 19
    },
    "dc37992": {
        "type": "destinationcharger",
        "statId": "dc37992",
        "statNm": "삼척 원더풀",
        "bnm": "데스티네이션차저",
        "lat": 37.429361,
        "lng": 129.182966,
        "addr": "강원특별자치도 삼척시 동해대로 3852",
        "phone": "033-575-5189",
        "webSite": null,
        "accessHours": "고객과 게스트가 연중무휴 24시간 이용 가능.",
        "stallCount": 3,
        "powerKilowattL": 16
    },
    "seoulseochosupercharger": {
        "type": "destinationcharger",
        "statId": "seoulseochosupercharger",
        "statNm": "서울 서초 - 쌍용플래티넘",
        "bnm": "데스티네이션차저",
        "lat": 37.48406,
        "lng": 127.01732,
        "addr": "서울 서초구 서초중앙로 18, 쌍용플래티넘 B2F",
        "phone": "02-588-1586",
        "webSite": "https://xn--x50b76j1yi22b93gtplrmknhe.apti.co.kr/aptHome/",
        "accessHours": "고객과 게스트가 연중무휴 24시간 이용 가능. 직접 주차",
        "stallCount": 8,
        "powerKilowattL": 7
    },
    "seoulseongsusupercharger": {
        "type": "destinationcharger",
        "statId": "seoulseongsusupercharger",
        "statNm": "서울 왕십리(5층)",
        "bnm": "데스티네이션차저",
        "lat": 37.5604,
        "lng": 127.0386,
        "addr": "서울 성동구 왕십리광장로 17, 비트플렉스 5F",
        "phone": "02-2200-1000",
        "webSite": "http://www.bitplex.co.kr/",
        "accessHours": "일반인이 연중무휴 24시간 이용 가능. 직접 주차",
        "stallCount": 3,
        "powerKilowattL": 7
    },
    "seolleungsupercharger": {
        "type": "destinationcharger",
        "statId": "seolleungsupercharger",
        "statNm": "서울 강남 - 센터필드",
        "bnm": "데스티네이션차저",
        "lat": 37.503216,
        "lng": 127.04162,
        "addr": "서울 강남구 테헤란로 231 센터필드 B5F",
        "phone": "080-617-1399",
        "webSite": null,
        "accessHours": "일반인이 연중무휴 24시간 이용 가능. 직접 주차",
        "stallCount": 12,
        "powerKilowattL": 3
    },
    "gangbuksupercharger": {
        "type": "destinationcharger",
        "statId": "gangbuksupercharger",
        "statNm": "서울 강북 - 안토",
        "bnm": "데스티네이션차저",
        "lat": 37.66375,
        "lng": 127.00871,
        "addr": "서울 강북구 삼양로 689, 파라스파라 RF/1F",
        "phone": "02-3408-5000",
        "webSite": "https://www.paraspara.co.kr/",
        "accessHours": "일반인이 연중무휴 24시간 이용 가능. 직접 주차",
        "stallCount": 2,
        "powerKilowattL": 7
    },
    "Misasupercharger": {
        "type": "destinationcharger",
        "statId": "Misasupercharger",
        "statNm": "서울 청량리 롯데백화점",
        "bnm": "데스티네이션차저",
        "lat": 37.58085,
        "lng": 127.04786,
        "addr": "서울 동대문구 왕산로 214, 롯데백화점 청량리점 M5F",
        "phone": null,
        "webSite": null,
        "accessHours": "일반인이 연중무휴 24시간 이용 가능. 직접 주차",
        "stallCount": 6,
        "powerKilowattL": 7
    },
    "seongsudtowerq322": {
        "type": "destinationcharger",
        "statId": "seongsudtowerq322",
        "statNm": "서울 성수 - D Tower",
        "bnm": "데스티네이션차저",
        "lat": 37.544,
        "lng": 127.0442,
        "addr": "서울 성동구 왕십리로 83-21, 서울포레스트D타워 B5F",
        "phone": null,
        "webSite": null,
        "accessHours": "연중무휴 24시간 이용 가능 주차비가 부과됩니다. 직접 주차",
        "stallCount": 3,
        "powerKilowattL": 7
    },
    "sejongsupercharger": {
        "type": "destinationcharger",
        "statId": "sejongsupercharger",
        "statNm": "세종 어진 - AK플라자",
        "bnm": "데스티네이션차저",
        "lat": 36.5003,
        "lng": 127.25686,
        "addr": "세종특별자치시 다솜1로 20 KT&G 세종타워C(지하2층, 14구역)",
        "phone": null,
        "webSite": null,
        "accessHours": "일반인이 연중무휴 24시간 이용 가능. 직접 주차",
        "stallCount": 3,
        "powerKilowattL": 7
    },
    "dc41685": {
        "type": "destinationcharger",
        "statId": "dc41685",
        "statNm": "소설호텔",
        "bnm": "데스티네이션차저",
        "lat": 37.4863566,
        "lng": 127.0139677,
        "addr": "서울 서초구 반포대로14길 53",
        "phone": "02-507-0505",
        "webSite": "http://www.snowhotel.co.kr/",
        "accessHours": "고객과 게스트가 연중무휴 24시간 이용 가능.",
        "stallCount": 2,
        "powerKilowattL": 6
    },
    "suyusupercharger": {
        "type": "destinationcharger",
        "statId": "suyusupercharger",
        "statNm": "서울 수유 - 에피소드 수유",
        "bnm": "데스티네이션차저",
        "lat": 37.6366748,
        "lng": 127.0234865,
        "addr": "서울 강북구 도봉로 315, 에피소드 수유 838 B4F",
        "phone": null,
        "webSite": null,
        "accessHours": "일반인이 연중무휴 24시간 이용 가능. 직접 주차",
        "stallCount": 2,
        "powerKilowattL": 7
    },
    "dc1025781": {
        "type": "destinationcharger",
        "statId": "dc1025781",
        "statNm": "스테이폴리오 - 모여집",
        "bnm": "데스티네이션차저",
        "lat": 37.5760859,
        "lng": 126.9339484,
        "addr": "서울 서대문구 연희로31길 30-4",
        "phone": "1670-4123",
        "webSite": "https://www.stayfolio.com/journal/picks/moyeohouse",
        "accessHours": "고객과 게스트가 연중무휴 24시간 이용 가능. 직접 주차",
        "stallCount": 1,
        "powerKilowattL": 7
    },
    "dc27266": {
        "type": "destinationcharger",
        "statId": "dc27266",
        "statNm": "씨에스 호텔 & 리조트",
        "bnm": "데스티네이션차저",
        "lat": 33.242922,
        "lng": 126.420435,
        "addr": "제주특별자치도 서귀포시 중문관광로 198",
        "phone": "064-735-3000",
        "webSite": "http://www.seaes.co.kr/",
        "accessHours": "고객과 게스트가 연중무휴 24시간 이용 가능.",
        "stallCount": 2,
        "powerKilowattL": 16
    },
    "gyeonggianyangsupercharger": {
        "type": "destinationcharger",
        "statId": "gyeonggianyangsupercharger",
        "statNm": "안양 CGV 평촌",
        "bnm": "데스티네이션차저",
        "lat": 37.39301,
        "lng": 126.96228,
        "addr": "경기 안양시 동안구 관평로170번길 33, CGV 평촌 7F",
        "phone": null,
        "webSite": null,
        "accessHours": "일반인이 연중무휴 24시간 이용 가능. 직접 주차(주차비 있음)",
        "stallCount": 3,
        "powerKilowattL": 7
    },
    "yangyangsupercharger": {
        "type": "destinationcharger",
        "statId": "yangyangsupercharger",
        "statNm": "양양 - 설해원",
        "bnm": "데스티네이션차저",
        "lat": 38.05419,
        "lng": 128.66058,
        "addr": "강원특별자치도 양양군 손양면 공항로 230, 설해원 리조트",
        "phone": null,
        "webSite": "https://www.seolhaeone.com/",
        "accessHours": "일반인이 연중무휴 24시간 이용 가능. 직접 주차",
        "stallCount": 5,
        "powerKilowattL": 7
    },
    "yeojusupercharger": {
        "type": "destinationcharger",
        "statId": "yeojusupercharger",
        "statNm": "여주 - 신세계프리미엄아울렛",
        "bnm": "데스티네이션차저",
        "lat": 37.2402517,
        "lng": 127.6137826,
        "addr": "경기 여주시 명품로 360, 여주프리미엄아울렛",
        "phone": "1644-4001",
        "webSite": "https://www.premiumoutlets.co.kr/yeoju/",
        "accessHours": "일반인이 연중무휴 24시간 이용 가능. 직접 주차",
        "stallCount": 11,
        "powerKilowattL": 7
    },
    "incheonyeongjonggrandhyatthotelwestkr": {
        "type": "destinationcharger",
        "statId": "incheonyeongjonggrandhyatthotelwestkr",
        "statNm": "인천 영종 - 그랜드하얏트 West",
        "bnm": "데스티네이션차저",
        "lat": 37.4398,
        "lng": 126.4561,
        "addr": "인천 중구 영종해안남로321번길 208",
        "phone": null,
        "webSite": null,
        "accessHours": "일반인이 연중무휴 24시간 이용 가능. 직접 주차",
        "stallCount": 6,
        "powerKilowattL": 7
    },
    "yonginsupercharger": {
        "type": "destinationcharger",
        "statId": "yonginsupercharger",
        "statNm": "용인 기흥 - 롯데프리미엄아울렛",
        "bnm": "데스티네이션차저",
        "lat": 37.225226,
        "lng": 127.121328,
        "addr": "경기 용인시 기흥구 신고매로 124 , 롯데프리미엄아울렛 기흥점 B3F",
        "phone": null,
        "webSite": null,
        "accessHours": "일반인이 연중무휴 24시간 이용 가능. 직접 주차",
        "stallCount": 6,
        "powerKilowattL": 7
    },
    "euiwangsupercharger": {
        "type": "destinationcharger",
        "statId": "euiwangsupercharger",
        "statNm": "의왕 - 롯데프리미엄아울렛",
        "bnm": "데스티네이션차저",
        "lat": 37.3756355,
        "lng": 127.0094715,
        "addr": "경기 의왕시 바라산로 1, 롯데프리미엄아울렛 의왕점 B1F",
        "phone": "1577-0001",
        "webSite": "https://www.lotteshopping.com/main/main",
        "accessHours": "일반인이 연중무휴 24시간 이용 가능. 직접 주차(09:30~21:30 이내 충전 가능)",
        "stallCount": 3,
        "powerKilowattL": 7
    },
    "dc585988": {
        "type": "destinationcharger",
        "statId": "dc585988",
        "statNm": "이븐데일 컨트리클럽",
        "bnm": "데스티네이션차저",
        "lat": 36.6828438,
        "lng": 127.6039669,
        "addr": "충북 청주시 상당구 미원면 대신2길 31",
        "phone": "043-288-1000",
        "webSite": "www.evendale.co.kr",
        "accessHours": "일반인이 연중무휴 24시간 이용 가능. 직접 주차",
        "stallCount": 2,
        "powerKilowattL": 19
    },
    "dc28101": {
        "type": "destinationcharger",
        "statId": "dc28101",
        "statNm": "임피리얼 팰리스 부티크 호텔 이태원",
        "bnm": "데스티네이션차저",
        "lat": 37.535315,
        "lng": 126.998264,
        "addr": "서울 용산구 이태원로 221",
        "phone": "02-3702-8000",
        "webSite": "http://www.imperialpalaceboutiquehotel.com/eng/index.do",
        "accessHours": "고객과 게스트가 연중무휴 24시간 이용 가능.",
        "stallCount": 2,
        "powerKilowattL": 16
    },
    "jeonjusupercharger": {
        "type": "destinationcharger",
        "statId": "jeonjusupercharger",
        "statNm": "전주 - 효자몰 (지하2층)",
        "bnm": "데스티네이션차저",
        "lat": 35.80698,
        "lng": 127.11566,
        "addr": "전북특별자치도 전주시 완산구 용머리로 45전북특별자치도 전주시 완산구 용머리로 45, 몰오브효자 B2F",
        "phone": null,
        "webSite": null,
        "accessHours": "일반인이 연중무휴 24시간 이용 가능. 직접 주차(주차비 있음)",
        "stallCount": 3,
        "powerKilowattL": 7
    },
    "dc585981": {
        "type": "destinationcharger",
        "statId": "dc585981",
        "statNm": "제일볼링센터",
        "bnm": "데스티네이션차저",
        "lat": 35.1719316,
        "lng": 126.9222181,
        "addr": "광주 북구 서방로 83",
        "phone": null,
        "webSite": null,
        "accessHours": "일반인이 연중무휴 24시간 이용 가능. 직접 주차",
        "stallCount": 4,
        "powerKilowattL": 7
    },
    "cheongnasupercharger": {
        "type": "destinationcharger",
        "statId": "cheongnasupercharger",
        "statNm": "인천 청라 - 스퀘어7",
        "bnm": "데스티네이션차저",
        "lat": 37.53236,
        "lng": 126.64166,
        "addr": "인천 서구 청라루비로 76, 스퀘어7",
        "phone": null,
        "webSite": null,
        "accessHours": "일반인이 연중무휴 24시간 이용 가능. 직접 주차",
        "stallCount": 4,
        "powerKilowattL": 7
    },
    "chuncheonsupercharger": {
        "type": "destinationcharger",
        "statId": "chuncheonsupercharger",
        "statNm": "춘천 - ENTA 2022",
        "bnm": "데스티네이션차저",
        "lat": 37.86326,
        "lng": 127.74814,
        "addr": "강원특별자치도 춘천시 후석로 120, 엔타2022 지하2층",
        "phone": null,
        "webSite": null,
        "accessHours": "일반인이 연중무휴 24시간 이용 가능. 직접 주차",
        "stallCount": 6,
        "powerKilowattL": 7
    },
    "chungjusupercharger": {
        "type": "destinationcharger",
        "statId": "chungjusupercharger",
        "statNm": "충주 - 홈마트",
        "bnm": "데스티네이션차저",
        "lat": 37.0016,
        "lng": 127.83573,
        "addr": "충북 충주시 대소원면 기업도시로 26, 홈마트",
        "phone": "043-846-7796",
        "webSite": null,
        "accessHours": "일반인이 연중무휴 24시간 이용 가능. 직접 주차",
        "stallCount": 7,
        "powerKilowattL": 7
    },
    "superchargerseongnamakr": {
        "type": "destinationcharger",
        "statId": "superchargerseongnamakr",
        "statNm": "성남 판교 - 카카오아지트",
        "bnm": "데스티네이션차저",
        "lat": 37.3953,
        "lng": 127.1104,
        "addr": "경기 성남시 분당구 판교역로 166, 카카오 판교 아지트 B2F",
        "phone": null,
        "webSite": null,
        "accessHours": "일반인이 연중무휴 24시간 이용 가능. 직접 주차",
        "stallCount": 2,
        "powerKilowattL": 10
    },
    "dc590587": {
        "type": "destinationcharger",
        "statId": "dc590587",
        "statNm": "카페인W",
        "bnm": "데스티네이션차저",
        "lat": 37.65188,
        "lng": 126.650472,
        "addr": "경기 김포시 양촌읍 김포한강4로 292-1",
        "phone": "070-7722-3330",
        "webSite": null,
        "accessHours": "일반인이 연중무휴 24시간 이용 가능. 직접 주차",
        "stallCount": 3,
        "powerKilowattL": 19
    },
    "dc572072": {
        "type": "destinationcharger",
        "statId": "dc572072",
        "statNm": "코리아 골프 연습장",
        "bnm": "데스티네이션차저",
        "lat": 35.081845,
        "lng": 128.97374,
        "addr": "부산 사하구 장림번영로103번길 39",
        "phone": "051-264-6378",
        "webSite": null,
        "accessHours": "고객과 게스트가 연중무휴 24시간 이용 가능. 직접 주차",
        "stallCount": 2,
        "powerKilowattL": 7
    },
    "TruelLamerHotelsokchokr": {
        "type": "destinationcharger",
        "statId": "TruelLamerHotelsokchokr",
        "statNm": "트루엘라메르",
        "bnm": "데스티네이션차저",
        "lat": 38.194136,
        "lng": 128.576787,
        "addr": "강원특별자치도 속초시 동해대로 4201",
        "phone": null,
        "webSite": null,
        "accessHours": "고객과 게스트가 연중무휴 24시간 이용 가능. 프론트 데스크를 참조하세요",
        "stallCount": 4,
        "powerKilowattL": null
    },
    "superchargerpajumunsterdam": {
        "type": "destinationcharger",
        "statId": "superchargerpajumunsterdam",
        "statNm": "파주 - 뮌스터담",
        "bnm": "데스티네이션차저",
        "lat": 37.726815,
        "lng": 126.783557,
        "addr": "경기 파주시 운정로 113-175",
        "phone": null,
        "webSite": null,
        "accessHours": "일반인이 연중무휴 24시간 이용 가능. 직접 주차",
        "stallCount": 3,
        "powerKilowattL": 7
    },
    "seongnamalphadome2supercharger": {
        "type": "destinationcharger",
        "statId": "seongnamalphadome2supercharger",
        "statNm": "성남 판교 - 테크원",
        "bnm": "데스티네이션차저",
        "lat": 37.3955193,
        "lng": 127.112237,
        "addr": "경기 성남시 분당구 분당내곡로 131",
        "phone": null,
        "webSite": null,
        "accessHours": "일반인이 연중무휴 24시간 이용 가능. 직접 주차",
        "stallCount": 2,
        "powerKilowattL": 7
    },
    "dc79999": {
        "type": "destinationcharger",
        "statId": "dc79999",
        "statNm": "포레스트 96",
        "bnm": "데스티네이션차저",
        "lat": 35.0638023,
        "lng": 126.988657,
        "addr": "전남 화순군 화순읍 신기중앙길 2",
        "phone": "061-375-2404",
        "webSite": "https://www.instagram.com/cafe_forrest96/",
        "accessHours": "고객과 게스트가 연중무휴 24시간 이용 가능.",
        "stallCount": 2,
        "powerKilowattL": 7
    },
    "dc27195": {
        "type": "destinationcharger",
        "statId": "dc27195",
        "statNm": "포시즌스 호텔 서울",
        "bnm": "데스티네이션차저",
        "lat": 37.57065,
        "lng": 126.975399,
        "addr": "서울 종로구 새문안로 97",
        "phone": "02-6388-5000",
        "webSite": "http://www.fourseasons.com/seoul/",
        "accessHours": "고객과 게스트가 연중무휴 24시간 이용 가능.",
        "stallCount": 2,
        "powerKilowattL": 16
    },
    "pohangsupercharger": {
        "type": "destinationcharger",
        "statId": "pohangsupercharger",
        "statNm": "포항",
        "bnm": "데스티네이션차저",
        "lat": 36.059093,
        "lng": 129.320555,
        "addr": "경북 포항시 북구 흥해읍 동해대로 878, 포항오토파크",
        "phone": null,
        "webSite": null,
        "accessHours": "일반인이 연중무휴 24시간 이용 가능. 직접 주차",
        "stallCount": 14,
        "powerKilowattL": 7
    },
    "dc28513": {
        "type": "destinationcharger",
        "statId": "dc28513",
        "statNm": "한화리조트 설악 쏘라노",
        "bnm": "데스티네이션차저",
        "lat": 38.2097711,
        "lng": 128.5276946,
        "addr": "강원특별자치도 속초시 미시령로2983번길 111",
        "phone": "033-630-5500",
        "webSite": "http://www.hanwharesort.co.kr/irsweb/resort3/resort/rs_room.asp?bp_cd=0101",
        "accessHours": "고객과 게스트가 연중무휴 24시간 이용 가능.",
        "stallCount": 3,
        "powerKilowattL": 16
    },
    "dc28516": {
        "type": "destinationcharger",
        "statId": "dc28516",
        "statNm": "한화리조트 해운대 티볼리",
        "bnm": "데스티네이션차저",
        "lat": 35.154582,
        "lng": 129.145004,
        "addr": "부산 해운대구 마린시티3로 52",
        "phone": "051-749-5500",
        "webSite": "http://www.hanwharesort.co.kr/irsweb/resort3/resort/rs_room.asp?bp_cd=0800",
        "accessHours": "고객과 게스트가 연중무휴 24시간 이용 가능.",
        "stallCount": 3,
        "powerKilowattL": 7
    },
    "52388": {
        "type": "destinationcharger",
        "statId": "52388",
        "statNm": "포춘테일",
        "bnm": "데스티네이션차저",
        "lat": 37.84274,
        "lng": 127.13151,
        "addr": "경기 포천시 동교로 15-14",
        "phone": null,
        "webSite": null,
        "accessHours": "고객과 게스트가 연중무휴 24시간 이용 가능. 직접 주차",
        "stallCount": 2,
        "powerKilowattL": 10
    },
    "52607": {
        "type": "destinationcharger",
        "statId": "52607",
        "statNm": "럭셔리몰임팩트광주명품백화점",
        "bnm": "데스티네이션차저",
        "lat": 35.14378,
        "lng": 126.82201,
        "addr": "광주 광산구 상무대로 509",
        "phone": "062-946-3333",
        "webSite": "www.impactuno.com",
        "accessHours": "일반인이 연중무휴 24시간 이용 가능. 직접 주차",
        "stallCount": 5,
        "powerKilowattL": 10
    },
    "404264": {
        "type": "destinationcharger",
        "statId": "404264",
        "statNm": "한일렌트카",
        "bnm": "데스티네이션차저",
        "lat": 35.8025,
        "lng": 127.0963,
        "addr": "전북특별자치도 전주시 완산구 쑥고개로 301-15",
        "phone": "063-255-8166",
        "webSite": null,
        "accessHours": "고객과 게스트가 연중무휴 24시간 이용 가능. 프론트 데스크를 참조하세요",
        "stallCount": 3,
        "powerKilowattL": null
    },
    "ibisambassadorhotelincheonairport": {
        "type": "destinationcharger",
        "statId": "ibisambassadorhotelincheonairport",
        "statNm": "이비스스타일앰베서더호텔 에어포트",
        "bnm": "데스티네이션차저",
        "lat": 37.481,
        "lng": 126.42,
        "addr": "인천 중구 제2터미널대로 340",
        "phone": null,
        "webSite": null,
        "accessHours": "일반인이 연중무휴 24시간 이용 가능. 직접 주차",
        "stallCount": 21,
        "powerKilowattL": 7
    },
    "54749": {
        "type": "destinationcharger",
        "statId": "54749",
        "statNm": "사운즈 한남",
        "bnm": "데스티네이션차저",
        "lat": 37.5337,
        "lng": 127.0022,
        "addr": "서울 용산구 대사관로 35",
        "phone": "02-511-7443",
        "webSite": "http://johcompany.com/sounds-urban-resort/",
        "accessHours": "고객과 게스트가 연중무휴 24시간 이용 가능. 발렛 서비스를 참조하세요",
        "stallCount": 1,
        "powerKilowattL": 10
    },
    "54828": {
        "type": "destinationcharger",
        "statId": "54828",
        "statNm": "스테이폴리오 - 송당아진",
        "bnm": "데스티네이션차저",
        "lat": 33.4771,
        "lng": 126.78561,
        "addr": "제주특별자치도 제주시 구좌읍 송당5길 46-78",
        "phone": "0504-0904-2420",
        "webSite": "https://www.stayfolio.com/journal/picks/songdangazin",
        "accessHours": "고객과 게스트가 연중무휴 24시간 이용 가능. 직접 주차",
        "stallCount": 1,
        "powerKilowattL": 10
    },
    "54831": {
        "type": "destinationcharger",
        "statId": "54831",
        "statNm": "스테이폴리오 - 빈티지제주",
        "bnm": "데스티네이션차저",
        "lat": 33.33462,
        "lng": 126.17522,
        "addr": "제주특별자치도 제주시 한경면 주전길 98-1",
        "phone": "0504-0904-2034",
        "webSite": "https://www.stayfolio.com/journal/picks/vintage-jeju",
        "accessHours": "고객과 게스트가 연중무휴 24시간 이용 가능. 직접 주차",
        "stallCount": 1,
        "powerKilowattL": 10
    },
    "54832": {
        "type": "destinationcharger",
        "statId": "54832",
        "statNm": "스테이폴리오 - 월령선인장",
        "bnm": "데스티네이션차저",
        "lat": 33.3762,
        "lng": 126.21593,
        "addr": "월령1길 10, 스테이폴리오 - 월령선인장",
        "phone": "0504-0904-2049",
        "webSite": "https://www.stayfolio.com/journal/picks/wollyeong-suninjang",
        "accessHours": "고객과 게스트가 연중무휴 24시간 이용 가능. 직접 주차",
        "stallCount": 1,
        "powerKilowattL": 10
    },
    "teslakrincheonyeongjonggrandhyatthoteleast": {
        "type": "destinationcharger",
        "statId": "teslakrincheonyeongjonggrandhyatthoteleast",
        "statNm": "인천 영종 - 그랜드하얏트 East",
        "bnm": "데스티네이션차저",
        "lat": 37.44031,
        "lng": 126.45744,
        "addr": "인천 중구 영종해안남로321번길 208",
        "phone": null,
        "webSite": null,
        "accessHours": "일반인이 연중무휴 24시간 이용 가능. 직접 주차",
        "stallCount": 6,
        "powerKilowattL": 7
    },
    "dc1128842": {
        "type": "destinationcharger",
        "statId": "dc1128842",
        "statNm": "스테이폴리오 - 제로플레이스",
        "bnm": "데스티네이션차저",
        "lat": 36.72417,
        "lng": 126.57611,
        "addr": "충남 서산시 해미면 일락골길 367-19",
        "phone": "0504-0904-2004",
        "webSite": "https://www.stayfolio.com/journal/picks/zeroplace",
        "accessHours": "일반인이 연중무휴 24시간 이용 가능. 직접 주차",
        "stallCount": 1,
        "powerKilowattL": 10
    },
    "dc1126931": {
        "type": "destinationcharger",
        "statId": "dc1126931",
        "statNm": "아이나비 프리미엄 스토어 인천점",
        "bnm": "데스티네이션차저",
        "lat": 37.54229,
        "lng": 126.67606,
        "addr": "인천 서구 심곡로 57",
        "phone": null,
        "webSite": "http://www.inavi.com/",
        "accessHours": "일반인이 연중무휴 24시간 이용 가능. 직접 주차",
        "stallCount": 1,
        "powerKilowattL": 10
    }
}
